{
	"name": "PL_ExecuteDataFlowCustomerPurchases",
	"properties": {
		"description": "Retry",
		"activities": [
			{
				"name": "DataFlowCustomerPurchase",
				"type": "ExecuteDataFlow",
				"dependsOn": [],
				"policy": {
					"timeout": "0.12:00:00",
					"retry": 1,
					"retryIntervalInSeconds": 30,
					"secureOutput": false,
					"secureInput": false
				},
				"userProperties": [],
				"typeProperties": {
					"dataflow": {
						"referenceName": "DF_Customer_Purchase",
						"type": "DataFlowReference"
					},
					"compute": {
						"coreCount": 8,
						"computeType": "General"
					},
					"traceLevel": "None",
					"cacheSinks": {
						"firstRowOnly": true
					}
				}
			}
		],
		"annotations": [],
		"lastPublishTime": "2025-08-10T18:00:17Z"
	},
	"type": "Microsoft.DataFactory/factories/pipelines"
}